kingunit/__init__.py
kingunit/generator.py
kingunit/init.py
kingunit/cmd/__init__.py
kingunit/cmd/cmd.py
kingunit/cmd/main.py
kingunit/config/__init__.py
kingunit/config/loader.py
kingunit/utils/__init__.py
kingunit/utils/loader.py
kingunit/utils/mail.py
kingunit/utils/validator.py
kingunit-0.0.10.dist-info/METADATA
kingunit-0.0.10.dist-info/WHEEL
kingunit-0.0.10.dist-info/top_level.txt
kingunit-0.0.10.dist-info/RECORD
