Metadata-Version: 2.1
Name: kingunit
Version: 0.0.10
Summary: KingUnit
Author-email: 东南dnf <zjy2414@outlook.com>
Project-URL: Home, https://github.com/zjy2414
Classifier: License :: OSI Approved :: MIT License
Requires-Dist: pyyaml
Requires-Dist: pytest
Requires-Dist: pytest-html
Requires-Dist: black
Requires-Dist: allure-pytest
Requires-Dist: typer[all]
